bask/__init__.py
bask/acquisition.py
bask/bayesgpr.py
bask/init.py
bask/optimizer.py
bask/priors.py
bask/searchcv.py
bask/utils.py
bask-0.10.9.dist-info/LICENSE
bask-0.10.9.dist-info/METADATA
bask-0.10.9.dist-info/WHEEL
bask-0.10.9.dist-info/RECORD
