Metadata-Version: 2.1
Name: bask
Version: 0.10.9
Summary: A fully Bayesian implementation of sequential model-based optimization
Home-page: https://github.com/kiudee/bayes-skopt
License: Apache-2.0
Keywords: optimization,bayesian,hyperparameters,robust
Author: Karlson Pfannschmidt
Author-email: kiudee@mail.upb.de
Requires-Python: >=3.8,<3.10
Classifier: Development Status :: 4 - Beta
Classifier: Intended Audience :: Developers
Classifier: Intended Audience :: Science/Research
Classifier: License :: OSI Approved :: Apache Software License
Classifier: Natural Language :: English
Classifier: Programming Language :: Python :: 3
Classifier: Programming Language :: Python :: 3.8
Classifier: Programming Language :: Python :: 3.9
Classifier: Topic :: Scientific/Engineering
Classifier: Topic :: Software Development
Provides-Extra: docs
Requires-Dist: Sphinx (>=3.1.2) ; extra == "docs"
Requires-Dist: arviz (>=0.10.0)
Requires-Dist: emcee (>=3.0.2)
Requires-Dist: matplotlib (>=3.3.0)
Requires-Dist: nbsphinx (>=0.7.1) ; extra == "docs"
Requires-Dist: nbsphinx-link (>=1.3.0) ; extra == "docs"
Requires-Dist: numpy (>=1.16,<1.24)
Requires-Dist: numpydoc (>=1.1.0) ; extra == "docs"
Requires-Dist: scikit-learn (>=1,<2)
Requires-Dist: scikit-optimize (>=0.9)
Requires-Dist: scipy (>=1.2)
Requires-Dist: tqdm (>=4.48.2)
Project-URL: Bug Tracker, https://github.com/kiudee/bayes-skopt/issues
Project-URL: Documentation, https://bayes-skopt.readthedocs.io
Project-URL: Repository, https://github.com/kiudee/bayes-skopt
